url_content_type_detector/__init__.py
url_content_type_detector/detector.py
url_content_type_detector/exceptions.py
url_content_type_detector-2026.1.2.dist-info/licenses/LICENSE
url_content_type_detector-2026.1.2.dist-info/METADATA
url_content_type_detector-2026.1.2.dist-info/WHEEL
url_content_type_detector-2026.1.2.dist-info/top_level.txt
url_content_type_detector-2026.1.2.dist-info/RECORD
