Metadata-Version: 2.4
Name: url-content-type-detector
Version: 2026.1.2
Summary: A utility to determine the content type of a URL.
Author-email: Kumar Sahil <krsahil8825@gmail.com>
Maintainer-email: Kumar Sahil <krsahil8825@gmail.com>
License: MIT
Project-URL: Homepage, https://krsahil8825.github.io/url_content_type_detector/
Project-URL: Documentation, https://krsahil8825.github.io/url_content_type_detector/docs/
Project-URL: Repository, https://github.com/krsahil8825/url_content_type_detector
Project-URL: Issues, https://github.com/krsahil8825/url_content_type_detector/issues
Keywords: url,content-type,detector,utility,python,url-content-type,content-type-detection,url-inspection,get-content-type,media-type,media-format-detection
Requires-Python: >=3.10
License-File: LICENSE
Requires-Dist: requests>=2.32.5
Requires-Dist: validators>=0.35.0
Provides-Extra: dev
Requires-Dist: pytest>=9.0.2; extra == "dev"
Requires-Dist: pylint>=3.1.0; extra == "dev"
Dynamic: license-file
